hera_filters/GIT_INFO
hera_filters/VERSION
hera_filters/__init__.py
hera_filters/dspec.py
hera_filters/version.py
hera_filters/data/__init__.py
hera_filters/data/noiselike_eor_diff.uvh5
hera_filters/data/simulated_eor.uvh5
hera_filters/data/uvd1.uvh5
hera_filters/data/uvd2.uvh5
hera_filters/data/uvd_1d_freqs.uvh5
hera_filters/data/uvd_1d_times.uvh5
hera_filters/data/uvd_1d_uvws.uvh5
hera_filters/data/uvd_bad_Nfreq.uvh5
hera_filters/data/uvd_bad_Ntimes.uvh5
hera_filters/data/uvd_bad_ants.uvh5
hera_filters/data/uvd_bad_bls.uvh5
hera_filters/data/uvd_bad_chan_width.uvh5
hera_filters/data/uvd_bad_int_time.uvh5
hera_filters/data/__pycache__/__init__.cpython-38.pyc
hera_filters/data/zen.2458042.17772.xx.HH.uvXA/flags
hera_filters/data/zen.2458042.17772.xx.HH.uvXA/header
hera_filters/data/zen.2458042.17772.xx.HH.uvXA/history
hera_filters/data/zen.2458042.17772.xx.HH.uvXA/vartable
hera_filters/data/zen.2458042.17772.xx.HH.uvXA/visdata
hera_filters/data/zen.all.xx.LST.1.06964.uvA/flags
hera_filters/data/zen.all.xx.LST.1.06964.uvA/header
hera_filters/data/zen.all.xx.LST.1.06964.uvA/history
hera_filters/data/zen.all.xx.LST.1.06964.uvA/vartable
hera_filters/data/zen.all.xx.LST.1.06964.uvA/visdata
hera_filters/tests/__init__.py
hera_filters/tests/test_dspec.py
hera_filters-0.1.1.dist-info/LICENSE
hera_filters-0.1.1.dist-info/METADATA
hera_filters-0.1.1.dist-info/WHEEL
hera_filters-0.1.1.dist-info/top_level.txt
hera_filters-0.1.1.dist-info/RECORD
